numpy_array_buffer/__init__.py
numpy_array_buffer/abstract_buffer.py
numpy_array_buffer/downsampling_buffer.py
numpy_array_buffer/ring_buffer.py
numpy_array_buffer-0.1.2.dist-info/LICENSE
numpy_array_buffer-0.1.2.dist-info/METADATA
numpy_array_buffer-0.1.2.dist-info/WHEEL
numpy_array_buffer-0.1.2.dist-info/top_level.txt
numpy_array_buffer-0.1.2.dist-info/RECORD
