Metadata-Version: 2.1
Name: numpy-array-buffer
Version: 0.1.2
Summary: Ringbuffer and downsampling buffer with numpy array backend
Home-page: https://github.com/maimonlab/numpy_array_buffer
Author: Thomas Mohren
Author-email: tlmohren@gmail.com
License: MIT license
Classifier: Development Status :: 2 - Pre-Alpha
Classifier: Intended Audience :: Developers
Classifier: License :: OSI Approved :: MIT License
Classifier: Natural Language :: English
Classifier: Programming Language :: Python :: 3
Classifier: Programming Language :: Python :: 3.6
Classifier: Programming Language :: Python :: 3.7
Classifier: Programming Language :: Python :: 3.8
Requires-Python: >=3.6
License-File: LICENSE
Requires-Dist: numpy
Provides-Extra: test
Requires-Dist: pytest ; extra == 'test'
Requires-Dist: coverage ; extra == 'test'
Requires-Dist: numpy-ringbuffer ; extra == 'test'
